finspect/__about__.py
finspect/__init__.py
finspect-0.0.0.dist-info/METADATA
finspect-0.0.0.dist-info/WHEEL
finspect-0.0.0.dist-info/licenses/LICENSE.txt
finspect-0.0.0.dist-info/RECORD
